curso_fiap_dev_ia/__init__.py
curso_fiap_dev_ia/core.py
curso_fiap_dev_ia_package-1.0.0.dist-info/METADATA
curso_fiap_dev_ia_package-1.0.0.dist-info/WHEEL
curso_fiap_dev_ia_package-1.0.0.dist-info/top_level.txt
curso_fiap_dev_ia_package-1.0.0.dist-info/RECORD
