Metadata-Version: 2.1
Name: curso_fiap_dev_ia-package
Version: 1.0.0
Summary: Descricao da sua lib curso_fiap_dev_ia
Home-page: https://github.com/dioleal
Author: Diogo Leonardo Leal
Author-email: diogoleal93@gmail.com
License: MIT
